cvideo/__init__.py
cvideo/centroidtracker.py
cvideo/video.py
cvideo-0.0.4.dist-info/METADATA
cvideo-0.0.4.dist-info/WHEEL
cvideo-0.0.4.dist-info/top_level.txt
cvideo-0.0.4.dist-info/RECORD
